shared/inverter.v
// inverter.v
module inverter (
    input wire a,
    output wire y
);
    assign y = ~a;
endmodule

shared/X5_run_tb.v
`timescale 1ns / 1ps
module inverter_tb;
reg a_tb;
wire y_tb;
inverter dut (
    .a(a_tb),
    .y(y_tb)
);
initial begin
$dumpfile("inverter_tb.vcd");
$dumpvars(0, inverter_tb);
$monitor("%0t: y_tb=%b", $time, y_tb);
#0 a_tb = 0;
#2 a_tb = 1;
#5 a_tb = 0;
#6 a_tb = 1;
#4 a_tb = 0;
#6 a_tb = 1;
#4 a_tb = 0;
#6 a_tb = 1;
#4 a_tb = 0;
#6 a_tb = 1;
#4 a_tb = 0;
end
endmodule

shared/inverter_tb.vcd
$date
	Mon Jun 16 09:54:33 2025
$end
$version
	Icarus Verilog
$end
$timescale
	1ps
$end
$scope module inverter_tb $end
$var wire 1 ! y_tb $end
$var reg 1 " a_tb $end
$scope module dut $end
$var wire 1 " a $end
$var wire 1 ! y $end
$upscope $end
$upscope $end
$enddefinitions $end
#0
$dumpvars
0"
1!
$end
#2000
0!
1"
#7000
1!
0"
#13000
0!
1"
#17000
1!
0"
#23000
0!
1"
#27000
1!
0"
#33000
0!
1"
#37000
1!
0"
#43000
0!
1"
#47000
1!
0"
